{
  "latitude": 47.63671875,
  "longitude": -122.6953125,
  "region_identifier": 1,
  "region_name": "Puget Sound",
  "retrieved_at": "2018-10-17T22:15:55+00:00",
  "units": "us",
  "today_summary": "Partly cloudy starting tonight.",
  "current_forecast": {
    "icon": "clear-day",
    "precip_per_hour": 0,
    "precip_probability": 0,
    "summary": "Clear",
    "temperature": 70.51,
    "temperature_feels_like": 70.51,
    "time": 1539812965,
    "wind_speed": 0.41
  },
  "hourly_forecast": [
    {
      "icon": "clear-day",
      "precip_per_hour": 0,
      "precip_probability": 0,
      "summary": "Clear",
      "temperature": 69.67,
      "temperature_feels_like": 69.67,
      "time": 1539810000,
      "wind_speed": 0.31
    },
    {
      "icon": "clear-day",
      "precip_per_hour": 0,
      "precip_probability": 0,
      "summary": "Clear",
      "temperature": 70.7,
      "temperature_feels_like": 70.7,
      "time": 1539813600,
      "wind_speed": 0.45
    },
    {
      "icon": "clear-day",
      "precip_per_hour": 0,
      "precip_probability": 0,
      "summary": "Clear",
      "temperature": 69.77,
      "temperature_feels_like": 69.77,
      "time": 1539817200,
      "wind_speed": 1.09
    },
    {
      "icon": "clear-day",
      "precip_per_hour": 0,
      "precip_probability": 0,
      "summary": "Clear",
      "temperature": 67.33,
      "temperature_feels_like": 67.33,
      "time": 1539820800,
      "wind_speed": 2.01
    },
    {
      "icon": "clear-day",
      "precip_per_hour": 0,
      "precip_probability": 0,
      "summary": "Clear",
      "temperature": 63.05,
      "temperature_feels_like": 63.05,
      "time": 1539824400,
      "wind_speed": 2.89
    },
    {
      "icon": "clear-night",
      "precip_per_hour": 0,
      "precip_probability": 0,
      "summary": "Clear",
      "temperature": 59.13,
      "temperature_feels_like": 59.13,
      "time": 1539828000,
      "wind_speed": 2.98
    },
    {
      "icon": "clear-night",
      "precip_per_hour": 0.0006,
      "precip_probability": 0.01,
      "summary": "Clear",
      "temperature": 56.52,
      "temperature_feels_like": 56.52,
      "time": 1539831600,
      "wind_speed": 3.08
    },
    {
      "icon": "clear-night",
      "precip_per_hour": 0.0013,
      "precip_probability": 0.01,
      "summary": "Clear",
      "temperature": 55.22,
      "temperature_feels_like": 55.22,
      "time": 1539835200,
      "wind_speed": 3.11
    },
    {
      "icon": "clear-night",
      "precip_per_hour": 0,
      "precip_probability": 0,
      "summary": "Clear",
      "temperature": 54.49,
      "temperature_feels_like": 54.49,
      "time": 1539838800,
      "wind_speed": 2.64
    },
    {
      "icon": "clear-night",
      "precip_per_hour": 0.0005,
      "precip_probability": 0.01,
      "summary": "Clear",
      "temperature": 53.65,
      "temperature_feels_like": 53.65,
      "time": 1539842400,
      "wind_speed": 2
    },
    {
      "icon": "clear-night",
      "precip_per_hour": 0,
      "precip_probability": 0,
      "summary": "Clear",
      "temperature": 52.89,
      "temperature_feels_like": 52.89,
      "time": 1539846000,
      "wind_speed": 2.13
    },
    {
      "icon": "clear-night",
      "precip_per_hour": 0.0015,
      "precip_probability": 0.01,
      "summary": "Clear",
      "temperature": 52.18,
      "temperature_feels_like": 52.18,
      "time": 1539849600,
      "wind_speed": 1.89
    },
    {
      "icon": "clear-night",
      "precip_per_hour": 0.0016,
      "precip_probability": 0.01,
      "summary": "Clear",
      "temperature": 51.61,
      "temperature_feels_like": 51.61,
      "time": 1539853200,
      "wind_speed": 1.79
    },
    {
      "icon": "partly-cloudy-night",
      "precip_per_hour": 0.0017,
      "precip_probability": 0.01,
      "summary": "Partly Cloudy",
      "temperature": 51.12,
      "temperature_feels_like": 51.12,
      "time": 1539856800,
      "wind_speed": 1.57
    },
    {
      "icon": "partly-cloudy-night",
      "precip_per_hour": 0.0009,
      "precip_probability": 0.01,
      "summary": "Partly Cloudy",
      "temperature": 50.6,
      "temperature_feels_like": 50.6,
      "time": 1539860400,
      "wind_speed": 0.83
    },
    {
      "icon": "partly-cloudy-night",
      "precip_per_hour": 0,
      "precip_probability": 0,
      "summary": "Mostly Cloudy",
      "temperature": 48.82,
      "temperature_feels_like": 48.82,
      "time": 1539864000,
      "wind_speed": 0.61
    },
    {
      "icon": "partly-cloudy-night",
      "precip_per_hour": 0,
      "precip_probability": 0,
      "summary": "Partly Cloudy",
      "temperature": 47.18,
      "temperature_feels_like": 47.18,
      "time": 1539867600,
      "wind_speed": 0.48
    },
    {
      "icon": "partly-cloudy-night",
      "precip_per_hour": 0,
      "precip_probability": 0,
      "summary": "Partly Cloudy",
      "temperature": 45.85,
      "temperature_feels_like": 45.85,
      "time": 1539871200,
      "wind_speed": 1.73
    },
    {
      "icon": "partly-cloudy-day",
      "precip_per_hour": 0,
      "precip_probability": 0,
      "summary": "Partly Cloudy",
      "temperature": 46.27,
      "temperature_feels_like": 46.27,
      "time": 1539874800,
      "wind_speed": 1.91
    },
    {
      "icon": "partly-cloudy-day",
      "precip_per_hour": 0,
      "precip_probability": 0,
      "summary": "Partly Cloudy",
      "temperature": 49.08,
      "temperature_feels_like": 49.08,
      "time": 1539878400,
      "wind_speed": 1.97
    },
    {
      "icon": "partly-cloudy-day",
      "precip_per_hour": 0,
      "precip_probability": 0,
      "summary": "Partly Cloudy",
      "temperature": 53.42,
      "temperature_feels_like": 53.42,
      "time": 1539882000,
      "wind_speed": 2.07
    },
    {
      "icon": "partly-cloudy-day",
      "precip_per_hour": 0,
      "precip_probability": 0,
      "summary": "Partly Cloudy",
      "temperature": 57.68,
      "temperature_feels_like": 57.68,
      "time": 1539885600,
      "wind_speed": 2
    },
    {
      "icon": "partly-cloudy-day",
      "precip_per_hour": 0,
      "precip_probability": 0,
      "summary": "Partly Cloudy",
      "temperature": 60.97,
      "temperature_feels_like": 60.97,
      "time": 1539889200,
      "wind_speed": 1.99
    },
    {
      "icon": "partly-cloudy-day",
      "precip_per_hour": 0,
      "precip_probability": 0,
      "summary": "Partly Cloudy",
      "temperature": 63.79,
      "temperature_feels_like": 63.79,
      "time": 1539892800,
      "wind_speed": 1.76
    },
    {
      "icon": "partly-cloudy-day",
      "precip_per_hour": 0,
      "precip_probability": 0,
      "summary": "Partly Cloudy",
      "temperature": 65.9,
      "temperature_feels_like": 65.9,
      "time": 1539896400,
      "wind_speed": 1.76
    },
    {
      "icon": "partly-cloudy-day",
      "precip_per_hour": 0,
      "precip_probability": 0,
      "summary": "Partly Cloudy",
      "temperature": 66.81,
      "temperature_feels_like": 66.81,
      "time": 1539900000,
      "wind_speed": 1.63
    },
    {
      "icon": "partly-cloudy-day",
      "precip_per_hour": 0,
      "precip_probability": 0,
      "summary": "Partly Cloudy",
      "temperature": 66.33,
      "temperature_feels_like": 66.33,
      "time": 1539903600,
      "wind_speed": 1.69
    },
    {
      "icon": "partly-cloudy-day",
      "precip_per_hour": 0.0002,
      "precip_probability": 0.01,
      "summary": "Partly Cloudy",
      "temperature": 64.91,
      "temperature_feels_like": 64.91,
      "time": 1539907200,
      "wind_speed": 1.69
    },
    {
      "icon": "clear-day",
      "precip_per_hour": 0,
      "precip_probability": 0,
      "summary": "Clear",
      "temperature": 61.94,
      "temperature_feels_like": 61.94,
      "time": 1539910800,
      "wind_speed": 1.78
    },
    {
      "icon": "partly-cloudy-night",
      "precip_per_hour": 0,
      "precip_probability": 0,
      "summary": "Partly Cloudy",
      "temperature": 58.19,
      "temperature_feels_like": 58.19,
      "time": 1539914400,
      "wind_speed": 2.07
    },
    {
      "icon": "partly-cloudy-night",
      "precip_per_hour": 0,
      "precip_probability": 0,
      "summary": "Partly Cloudy",
      "temperature": 55.21,
      "temperature_feels_like": 55.21,
      "time": 1539918000,
      "wind_speed": 2.25
    },
    {
      "icon": "partly-cloudy-night",
      "precip_per_hour": 0,
      "precip_probability": 0,
      "summary": "Partly Cloudy",
      "temperature": 53.81,
      "temperature_feels_like": 53.81,
      "time": 1539921600,
      "wind_speed": 2.26
    },
    {
      "icon": "partly-cloudy-night",
      "precip_per_hour": 0,
      "precip_probability": 0,
      "summary": "Partly Cloudy",
      "temperature": 53.12,
      "temperature_feels_like": 53.12,
      "time": 1539925200,
      "wind_speed": 2.23
    },
    {
      "icon": "clear-night",
      "precip_per_hour": 0.0003,
      "precip_probability": 0.01,
      "summary": "Clear",
      "temperature": 52.35,
      "temperature_feels_like": 52.35,
      "time": 1539928800,
      "wind_speed": 2.09
    },
    {
      "icon": "partly-cloudy-night",
      "precip_per_hour": 0.0002,
      "precip_probability": 0.01,
      "summary": "Partly Cloudy",
      "temperature": 51.65,
      "temperature_feels_like": 51.65,
      "time": 1539932400,
      "wind_speed": 2.13
    },
    {
      "icon": "partly-cloudy-night",
      "precip_per_hour": 0,
      "precip_probability": 0,
      "summary": "Partly Cloudy",
      "temperature": 50.9,
      "temperature_feels_like": 50.9,
      "time": 1539936000,
      "wind_speed": 1.91
    },
    {
      "icon": "partly-cloudy-night",
      "precip_per_hour": 0,
      "precip_probability": 0,
      "summary": "Partly Cloudy",
      "temperature": 50.15,
      "temperature_feels_like": 50.15,
      "time": 1539939600,
      "wind_speed": 1.84
    },
    {
      "icon": "partly-cloudy-night",
      "precip_per_hour": 0,
      "precip_probability": 0,
      "summary": "Partly Cloudy",
      "temperature": 49.2,
      "temperature_feels_like": 49.2,
      "time": 1539943200,
      "wind_speed": 1.97
    },
    {
      "icon": "partly-cloudy-night",
      "precip_per_hour": 0,
      "precip_probability": 0,
      "summary": "Partly Cloudy",
      "temperature": 48.27,
      "temperature_feels_like": 48.27,
      "time": 1539946800,
      "wind_speed": 1.8
    },
    {
      "icon": "partly-cloudy-night",
      "precip_per_hour": 0,
      "precip_probability": 0,
      "summary": "Partly Cloudy",
      "temperature": 47.19,
      "temperature_feels_like": 47.19,
      "time": 1539950400,
      "wind_speed": 1.65
    },
    {
      "icon": "clear-night",
      "precip_per_hour": 0,
      "precip_probability": 0,
      "summary": "Clear",
      "temperature": 46.88,
      "temperature_feels_like": 46.88,
      "time": 1539954000,
      "wind_speed": 1.46
    },
    {
      "icon": "clear-night",
      "precip_per_hour": 0,
      "precip_probability": 0,
      "summary": "Clear",
      "temperature": 45.95,
      "temperature_feels_like": 45.95,
      "time": 1539957600,
      "wind_speed": 1.42
    },
    {
      "icon": "clear-day",
      "precip_per_hour": 0.0003,
      "precip_probability": 0.01,
      "summary": "Clear",
      "temperature": 46.64,
      "temperature_feels_like": 46.64,
      "time": 1539961200,
      "wind_speed": 1.4
    },
    {
      "icon": "clear-day",
      "precip_per_hour": 0.0002,
      "precip_probability": 0.01,
      "summary": "Clear",
      "temperature": 49.25,
      "temperature_feels_like": 49.25,
      "time": 1539964800,
      "wind_speed": 1.39
    },
    {
      "icon": "clear-day",
      "precip_per_hour": 0,
      "precip_probability": 0,
      "summary": "Clear",
      "temperature": 53.59,
      "temperature_feels_like": 53.59,
      "time": 1539968400,
      "wind_speed": 1.47
    },
    {
      "icon": "clear-day",
      "precip_per_hour": 0,
      "precip_probability": 0,
      "summary": "Clear",
      "temperature": 57.96,
      "temperature_feels_like": 57.96,
      "time": 1539972000,
      "wind_speed": 1.36
    },
    {
      "icon": "clear-day",
      "precip_per_hour": 0,
      "precip_probability": 0,
      "summary": "Clear",
      "temperature": 61.22,
      "temperature_feels_like": 61.22,
      "time": 1539975600,
      "wind_speed": 1.43
    },
    {
      "icon": "clear-day",
      "precip_per_hour": 0,
      "precip_probability": 0,
      "summary": "Clear",
      "temperature": 64.48,
      "temperature_feels_like": 64.48,
      "time": 1539979200,
      "wind_speed": 1.58
    },
    {
      "icon": "clear-day",
      "precip_per_hour": 0,
      "precip_probability": 0,
      "summary": "Clear",
      "temperature": 66.96,
      "temperature_feels_like": 66.96,
      "time": 1539982800,
      "wind_speed": 1.69
    }
  ]
}